MANIFEST.in
README.md
setup.cfg
setup.py
bin/kachery-p2p
bin/kachery-p2p-cat
bin/kachery-p2p-find
bin/kachery-p2p-get-channels
bin/kachery-p2p-join-channel
bin/kachery-p2p-leave-channel
bin/kachery-p2p-link
bin/kachery-p2p-load
bin/kachery-p2p-node-info
bin/kachery-p2p-print-messages
bin/kachery-p2p-start-daemon
bin/kachery-p2p-stop-daemon
bin/kachery-p2p-store
kachery_p2p/__init__.py
kachery_p2p/_core2.py
kachery_p2p/_daemon_connection.py
kachery_p2p/_exceptions.py
kachery_p2p/_experimental_config.py
kachery_p2p/_feeds.py
kachery_p2p/_load_file.py
kachery_p2p/_local_kachery_storage.py
kachery_p2p/_misc.py
kachery_p2p/_mutables.py
kachery_p2p/_preventkeyboardinterrupt.py
kachery_p2p/_safe_pickle.py
kachery_p2p/_shellscript.py
kachery_p2p/_start_daemon.py
kachery_p2p/_store_file.py
kachery_p2p/_temporarydirectory.py
kachery_p2p/_testdaemon.py
kachery_p2p/cli.py
kachery_p2p/filelock.py
kachery_p2p/kachery-p2p-daemon-0.8.31.tgz
kachery_p2p/main.py
kachery_p2p/protocol_version.py
kachery_p2p.egg-info/PKG-INFO
kachery_p2p.egg-info/SOURCES.txt
kachery_p2p.egg-info/dependency_links.txt
kachery_p2p.egg-info/requires.txt
kachery_p2p.egg-info/top_level.txt
test/test_1.py