Metadata-Version: 1.2
Name: kachery-p2p
Version: 0.8.31
Summary: Peer-to-peer file sharing for data science
Home-page: https://github.com/flatironinstitute/kachery_p2p
Author: Jeremy Magland and Jeff Soules
Author-email: jmagland@flatironinstitute.org
License: UNKNOWN
Project-URL: Bug Tracker, https://github.com/flatironinstitute/kachery_p2p/issues
Platform: UNKNOWN
Classifier: Programming Language :: Python :: 3
Classifier: License :: OSI Approved :: Apache Software License
Classifier: Operating System :: OS Independent
